{"nroReuniao": 180, "dataReferencia": "2014-01-15", "dataPublicacao": "2014-01-23", "titulo": "180ª Reunião", "urlPdfAta": null, "textoAta": "\n\n<body link=blue vlink=purple>\n\n<div>\n\n<div><b>Sumário</b></div>\n\n<div><a\nhref=\"#_Toc378175529\">Evolução recente da economia</a></span></div>\n\n<div><a\nhref=\"#_Toc378175530\">Avaliação\nprospectiva das tendências da inflação</a></span></div>\n\n<div><a\nhref=\"#_Toc378175531\">Implementação\nda política monetária</a></span></div>\n\n<div><a\nhref=\"#_Toc378175532\">Inflação</a></span></div>\n\n<div><a\nhref=\"#_Toc378175533\">Atividade\neconômica</a></span></div>\n\n<div><a\nhref=\"#_Toc378175534\">Expectativas\ne sondagens</a></span></div>\n\n<div><a href=\"#_Toc378175535\">Mercado de trabalho</a></span></div>\n\n<div><a\nhref=\"#_Toc378175536\">Crédito\ne inadimplência</a></span></div>\n\n<div><a\nhref=\"#_Toc378175537\">Ambiente\nexterno</a></span></div>\n\n<div><a\nhref=\"#_Toc378175538\">Comércio\nexterior e reservas internacionais</a></span></div>\n\n<div><a\nhref=\"#_Toc378175539\">Mercado\nmonetário e operações de mercado aberto</a></span></div>\n\n<div><b>&nbsp;</b></div>\n\n<div><b>Data:</b> 14 e 15/01/2014</div>\n\n<div>&nbsp;</div>\n\n<div><b>Local:</b> Sala de reuniões do 8º andar (14/01) e do\n20º andar (15/01) do Edifício-Sede do Banco Central do Brasil – Brasília – DF</div>\n\n<div><b>Horário de início:</b> 16h31 (14/01) e 16h48 (15/01) </div>\n\n<div><b>Horário de término:</b> 19h36 (14/01) e 19h57\n(15/01) </div>\n\n<div>&nbsp;</div>\n\n<div><b>Presentes:</b></div>\n\n<div><b>Membros do Copom</b></div>\n\n<div>Alexandre Antonio Tombini\n– Presidente</div>\n\n<div>Aldo\nLuiz Mendes</div>\n\n<div>Altamir\nLopes</div>\n\n<div>Anthero\nde Moraes Meirelles</div>\n\n<div>Carlos\nHamilton Vasconcelos Araújo</div>\n\n<div>Luiz\nAwazu Pereira da Silva</div>\n\n<div>Luiz\nEdson Feltrim</div>\n\n<div>Sidnei\nCorrêa Marques</div>\n\n<div>&nbsp;</div>\n\n<div><b>Chefes de Departamento (presentes em 14/01)</b></div>\n\n<div>Bruno Walter Coelho\nSaraiva – Departamento de Assuntos Internacionais</div>\n\n<div>Daso Maranhão Coimbra\n– Departamento de Operações Bancárias e de Sistema de Pagamentos</div>\n\n<div>Eduardo José Araújo\nLima – Departamento de Estudos e Pesquisas (também presente em 15/01)</div>\n\n<div>João Henrique de\nPaula Freitas Simão – Departamento de Operações do Mercado Aberto</div>\n\n<div>Márcio Barreira de\nAyrosa Moreira – Departamento das Reservas Internacionais </div>\n\n<div>Renato Jansson Rosek\n– Departamento de Relacionamento com Investidores e Estudos Especiais</div>\n\n<div>Tulio José Lenti\nMaciel – Departamento Econômico</div>\n\n<div><b>&nbsp;</b></div>\n\n<div><b>Demais participantes (presentes em 14/01)</b></div>\n\n<div>Gustavo Paul Kurrle –\nAssessor de Imprensa</div>\n\n<div>Otávio Ribeiro Damaso\n– Chefe de Gabinete da Presidência</div>\n\n<div>&nbsp;</div>\n\n<div>Os membros do Copom\nanalisaram a evolução recente e as perspectivas para a economia brasileira e\npara a economia internacional, no contexto do regime de política monetária,\ncujo objetivo é atingir as metas fixadas pelo governo para a inflação.</div>\n\n<div>&nbsp;</div>\n\n<div><a name=\"_Toc361845888\"></a><a\nname=\"_Toc378175529\"></a></span><b>E</b><b>volução recente da\neconomia</b></div>\n\n<div><b>&nbsp;</b></div>\n\n<div class='lista1'><span class='lista1'>1.</span>\nA\ninflação medida pela variação do Índice Nacional de Preços ao Consumidor Amplo\n(IPCA) foi de 0,92% em dezembro, 0,13 ponto percentual (p.p.)\nmaior do que a registrada em dezembro de 2012. Dessa forma, a inflação\nacumulada em 2013 atingiu 5,91% (ante 5,84% em 2012). Os preços livres\naumentaram 7,29% em 2013 (6,56% em 2012); e os preços administrados, 1,54%\n(3,65% em 2012). Especificamente sobre os preços livres, os de bens\ncomercializáveis aumentaram 6,01% em 2013 (4,47% no ano anterior), e os de bens\nnão comercializáveis, 8,43% (8,46% em 2012). Por sua vez, os preços do segmento\nde alimentos e bebidas aumentaram 8,48% em 2013 (9,86% em 2012); e os dos\nserviços, 8,75% (mesmo valor observado em 2012). Em síntese, as informações\ndisponíveis sugerem certa persistência da inflação, o que reflete em parte o fato\nde a inflação de serviços seguir em níveis elevados. </div>\n\n<div>&nbsp;</div>\n\n<div class='lista1'><span class='lista1'>2.</span>\nA\nmédia das variações mensais das medidas de inflação subjacente, calculadas pelo\nBanco Central, passou de 0,54% em novembro para 0,76% em dezembro. Assim, a\nvariação acumulada em doze meses atingiu 6,28% (0,68 p.p.\nacima da registrada em dezembro de 2012). Especificamente, o núcleo do IPCA por\nmédias aparadas com suavização se deslocou de 0,45% em novembro para 0,58% em\ndezembro; o núcleo por dupla ponderação, de 0,52% para 0,79%; o núcleo por exclusão\nde monitorados e de alimentação no domicílio, de 0,60% para 0,96%; o núcleo por\nmédias aparadas sem suavização, de 0,55% para 0,72%; e o núcleo por exclusão,\nque descarta dez itens de alimentação no domicílio, bem como combustíveis, de\n0,57% para 0,74%. O índice de difusão ficou em 69,3% em dezembro (ante 70,7% no\nmesmo mês do ano anterior).</div>\n\n<div>&nbsp;</div>\n\n<div class='lista1'><span class='lista1'>3.</span>\nO\nÍndice Geral de Preços - Disponibilidade Interna (IGP-DI) avançou 0,69% em\ndezembro, na comparação mensal, e 5,52% no acumulado em doze meses (8,10% em 2012).\nO principal componente do IGP-DI, o Índice de Preços ao Produtor Amplo (IPA), aumentou\n5,07% em 2013 (9,13% em 2012), com recuo de 1,76% nos preços de produtos\nagropecuários em 2013 e elevação de 7,87% nos de produtos industriais. O Índice\nde Preços ao Consumidor (IPC), segundo componente mais importante do IGP-DI,\nvariou 5,63% em 2013 (5,74% em 2012); e o Índice Nacional de Custo da\nConstrução (INCC), componente de menor peso no IGP-DI, 8,09% (7,12% em 2012),\nem parte, reflexo de pressões de custos de mão de obra, que variaram 9,77% no\nperíodo. Por sua vez, o Índice de Preços ao Produtor/Indústria de Transformação\n(IPP/IT), calculado pelo Instituto Brasileiro de Geografia e Estatística\n(IBGE), aumentou 0,62% em novembro em relação ao mês anterior (5,47% em doze\nmeses). O Copom avalia que os efeitos do comportamento dos preços no atacado\nsobre a inflação para os consumidores dependerão das condições atuais e\nprospectivas da demanda e das expectativas dos formadores de preços em relação\nà trajetória futura da inflação.</div>\n\n<div>&nbsp;</div>\n\n<div class='lista1'><span class='lista1'>4.</span>\nO\nÍndice de Atividade Econômica do Banco Central (IBC-Br) incorpora estimativa\npara a produção mensal dos três setores da economia, bem como para impostos\nsobre produtos, e constitui importante indicador coincidente da atividade\neconômica. Em outubro, o IBC-Br variou 0,8% em relação ao mês anterior e 2,7%\nem relação a outubro de 2012. O <i>Purchasing</i><i> Managers'\nIndex</i> (PMI) composto referente ao Brasil apontou intensificação da\natividade econômica pelo quarto mês consecutivo em dezembro. Por sua vez, o\nÍndice de Confiança do Consumidor (ICC), da Fundação Getulio Vargas (FGV),\nrecuou em dezembro e, dessa forma, reverteu avanço observado no mês anterior,\nde acordo com a série livre de influências sazonais. Já a confiança do\nempresário industrial, medida pelo Índice de Confiança da Indústria (ICI), aumentou\nem dezembro, a exemplo do que havia ocorrido em novembro. O Índice de Confiança\nde Serviços (ICS) também avançou em dezembro. No que se refere à agricultura, o\nLevantamento Sistemático da Produção Agrícola (LSPA), do IBGE, projeta\ncrescimento de 0,7% na produção de grãos em 2014, em relação a 2013.</div>\n\n<div>&nbsp;</div>\n\n<div class='lista1'><span class='lista1'>5.</span>\nA\neconomia brasileira cresceu 2,2% no terceiro trimestre de 2013, em relação ao\nmesmo trimestre do ano anterior, após crescer 3,3% no segundo trimestre, na mesma\nbase de comparação. Segundo dados dessazonalizados pelo IBGE, após crescer 1,8%\nno segundo trimestre, o Produto Interno Bruto (PIB) diminuiu 0,5% no terceiro\ntrimestre, na comparação com o trimestre imediatamente anterior. Dessa forma, a\ntaxa de crescimento acumulada em quatro trimestres se deslocou de 2,0% para\n2,3%. Sob a ótica da demanda agregada, o consumo das famílias continuou em\nexpansão, com crescimento de 1,0% no terceiro trimestre, ante o anterior, e de\n2,3% em relação ao mesmo trimestre de 2012 – quadragésimo aumento consecutivo\nnessa base de comparação. Por sua vez, o consumo do governo cresceu 1,2% em\nrelação ao trimestre anterior e 2,3% em relação ao mesmo trimestre de 2012. Já\na Formação Bruta de Capital Fixo (FBCF) aumentou 7,3% em relação ao mesmo\ntrimestre de 2012, não obstante haver recuado 2,2% em relação ao trimestre\nanterior. </div>\n\n<div>&nbsp;</div>\n\n<div class='lista1'><span class='lista1'>6.</span>\nApós\ncrescimento de 0,6% em outubro, a atividade fabril recuou 0,2% em novembro, de\nacordo com a série livre de influências sazonais, divulgada pelo IBGE. Assim, a\nprodução industrial em novembro superou em 0,4% a observada em novembro de\n2012. Entre janeiro e novembro, a produção física da indústria aumentou 1,4% em\ncomparação ao mesmo período de 2012, com destaque para a produção de veículos\nautomotores (com expansão de 9,0%), bem como para a de outros equipamentos de\ntransporte, e refino de petróleo e produção de álcool (com expansão de 7,8% e\n7,7%, respectivamente). Note-se ainda que a produção aumentou em 16 ramos de\natividade, dos 27 pesquisados, nessa mesma base de comparação. O indicador PMI\ndo setor industrial aponta expansão em dezembro. De acordo com dados divulgados\npela Confederação Nacional da Indústria (CNI), o faturamento real da indústria\nde transformação cresceu 4,6% entre janeiro e outubro de 2013, comparativamente\nao mesmo período do ano anterior, e o número de horas trabalhadas cresceu 0,1%.</div>\n\n<div>&nbsp;</div>\n\n<div class='lista1'><span class='lista1'>7.</span>\nEntre\nas categorias de uso, de acordo com dados dessazonalizados pelo IBGE, a\nprodução de bens de capital recuou em novembro (2,6%); ao passo que a de bens\nintermediários, a de bens de consumo duráveis e a de bens semiduráveis e não\nduráveis aumentaram 1,2%, 0,3% e 0,3%, respectivamente. No que se refere à\nvariação acumulada em doze meses até novembro, houve crescimento de 11,6% na\nprodução de bens de capital e de 0,8% na de bens de consumo duráveis; recuo de\n0,4% na produção do setor de bens de consumo semiduráveis e não duráveis; e\nestabilidade na produção do setor de bens intermediários.</div>\n\n<div>&nbsp;</div>\n\n<div class='lista1'><span class='lista1'>8.</span>\nA\ntaxa de desemprego nas seis regiões metropolitanas cobertas pela Pesquisa\nMensal de Emprego (PME), sem ajuste sazonal, recuou para 4,6% em novembro,\nrepetindo, assim, o mínimo da série histórica observado em dezembro de 2012. A\ntaxa de desocupação também atingiu o mínimo da série histórica iniciada em\n2002, de acordo com a série dessazonalizada pelo Banco Central (5,1%), o que,\nem parte, reflete redução da população economicamente ativa (PEA). Ainda de\nacordo com a PME, o rendimento médio real habitual cresceu 3,0% em novembro,\ncomparado a igual mês do ano anterior; e a massa salarial real, 2,3%, na mesma\nbase de comparação. Dados divulgados pelo Ministério do Trabalho e Emprego\n(MTE) mostram criação de 47,5 mil postos de trabalho formais em novembro (ante\n46,1 mil em novembro de 2012). Em suma, dados disponíveis indicam estreita\nmargem de ociosidade no mercado de trabalho, embora existam alguns sinais de\nmoderação na margem.</div>\n\n<div>&nbsp;</div>\n\n<div class='lista1'><span class='lista1'>9.</span>\nDe\nacordo com dados da Pesquisa Mensal do Comércio (PMC), divulgada pelo IBGE, o\nvolume de vendas do comércio varejista ampliado cresceu 2,2% em outubro de\n2013, em relação ao mesmo mês do ano anterior, e o do comércio varejista\nrestrito, 5,3%. As variações mês a mês foram de 1,8% e de 0,2%,\nrespectivamente, de acordo com as séries dessazonalizadas. Em doze meses, a\ntaxa de crescimento do comércio ampliado foi de 3,9%, com expansão em todos os\ndez segmentos pesquisados. O Índice de Confiança do Comércio (ICOM), medido\npela FGV, registrou a quinta alta consecutiva em dezembro, em razão de melhoras\nna percepção da situação atual. O Copom avalia que a trajetória do comércio\ncontinuará sendo influenciada pelas transferências governamentais, pelo ritmo\nde crescimento da massa salarial real e pela expansão moderada do crédito.</div>\n\n<div>&nbsp;</div>\n\n<div class='lista1'><span class='lista1'>10.</span> O Nível de Utilização\nda Capacidade Instalada (Nuci) na indústria de\ntransformação, calculado pela FGV, sem ajuste sazonal, alcançou 84,9% em\ndezembro (84,8% em dezembro de 2012) e, na série dessazonalizada pela FGV,\n84,2%. A utilização da capacidade no setor de bens de capital ficou em 81,8%.\nNo setor de bens de consumo, de bens intermediários e de materiais de\nconstrução, a utilização da capacidade se posicionou em 84,6%, 85,1% e 90,1%,\nrespectivamente. Por sua vez, a absorção de bens de capital cresceu 11,3% no\nperíodo de doze meses até novembro.</div>\n\n<div>&nbsp;</div>\n\n<div class='lista1'><span class='lista1'>11.</span> O saldo da balança\ncomercial alcançou US$2,6 bilhões em 2013 (US$19,4 bilhões em 2012). Esse\nresultado adveio de exportações de US$242,2 bilhões e de importações de\nUS$239,6 bilhões, com recuo de 0,2% e avanço de 7,4%, respectivamente, em\nrelação ao ano anterior. Por sua vez, o <i>deficit</i> em transações correntes acumulado em doze meses\natingiu US$81,1 bilhões em novembro, equivalente a 3,7% do PIB. Já os\ninvestimentos estrangeiros diretos totalizaram US$62,8 bilhões em doze meses\naté novembro, equivalentes a 2,8% do PIB. </div>\n\n<div>&nbsp;</div>\n\n<div class='lista1'><span class='lista1'>12.</span> Na economia global, as\nperspectivas apontam ritmo mais intenso da atividade em importantes economias\nmaduras. Na Europa, em que pese avanços recentes, altas taxas de desemprego,\naliadas à consolidação fiscal e incertezas políticas, constituem elementos de\ncontenção de investimentos e do crescimento. Note-se que indicadores\nantecedentes compostos, divulgados pela Organização para a Cooperação e\nDesenvolvimento Econômico (OCDE), referentes a novembro, e indicadores\ncoincidentes PMI, referentes a dezembro, apontam melhoras na margem em diversas\neconomias avançadas e emergentes, em especial no setor manufatureiro, com\nperspectivas de crescimento compatíveis com a tendência ou acima desta. Em\nrelação à política monetária, o banco central norte-americano (<i>Federal Reserve</i>) iniciou processo de\nredução gradual do programa de compra de ativos, no entanto, de modo geral,\nprevalecem posturas acomodatícias nas economias maduras. Da mesma forma, nas\neconomias emergentes, a política monetária se apresenta predominantemente\nexpansionista. A inflação continua em níveis moderados ou baixos nos Estados\nUnidos (EUA), na Zona do Euro e no Japão.</div>\n\n<div>&nbsp;</div>\n\n<div class='lista1'><span class='lista1'>13.</span> O preço do barril de\npetróleo do tipo <i>Brent</i> recuou\nligeiramente desde a última reunião do Copom. Cabe ressaltar que a complexidade\ngeopolítica que envolve o setor de petróleo tende a acentuar o comportamento\nvolátil dos preços, que é reflexo, também, da baixa previsibilidade de alguns\ncomponentes da demanda global e do fato de o crescimento da oferta depender de\nprojetos de investimentos de longa maturação e de elevado risco. Desde a última\nreunião do Copom, os preços internacionais das <i>commodities</i> agrícolas recuaram 3,3%, e os preços das <i>commodities</i> metálicas aumentaram 4,9%. Por\nsua vez, o Índice de Preços de Alimentos, calculado pela Organização das Nações\nUnidas para Agricultura e Alimentação (FAO), recuou 3,5% em doze meses até\ndezembro de 2013.</div>\n\n<div>&nbsp;</div>\n\n<div><a\nname=\"_Toc378175530\"></a></span><b>Avaliação\nprospectiva das tendências da inflação</b></div>\n\n<div>&nbsp;</div>\n\n<div class='lista1'><span class='lista1'>14.</span>\nOs\nchoques identificados, e seus impactos, foram reavaliados de acordo com o novo\nconjunto de informações disponível. O cenário considerado nas simulações\ncontempla as seguintes hipóteses:</div>\n\n<div>a) projeta-se\nestabilidade nos preços da gasolina e do gás de bujão, para o acumulado de\n2014;</div>\n\n<div>b) a projeção aponta\nelevação de 7,5%, para o acumulado de 2014, na tarifa residencial de\neletricidade;</div>\n\n<div>c) projeta-se\nestabilidade da tarifa de telefonia fixa, para o acumulado de 2014; </div>\n\n<div>d) a projeção de\nreajuste, construída item a item, para o conjunto de preços administrados por\ncontrato e monitorados, para o acumulado de 2014, foi mantida em 4,5%, mesmo\nvalor considerado na reunião do Copom de novembro; e</div>\n\n<div>e) a projeção de\nreajuste para o conjunto dos preços administrados por contrato e monitorados,\npara o acumulado de 2015, é de 4,5%. Essas projeções baseiam-se em modelos de\ndeterminação endógena de preços administrados, que consideram, entre outras\nvariáveis, componentes sazonais, inflação de preços livres e inflação medida\npelo Índice Geral de Preços (IGP).</div>\n\n<div>&nbsp;</div>\n\n<div class='lista1'><span class='lista1'>15.</span> A trajetória estimada\npara a taxa do <i>swap</i> pré-DI de 360\ndias indica <i>spread</i> sobre a taxa\nSelic, no cenário de referência, de 0 ponto base (p.b.)\ne 42 p.b. para o quarto trimestre de 2014 e de 2015,\nrespectivamente.</div>\n\n<div>&nbsp;</div>\n\n<div class='lista1'><span class='lista1'>16.</span> Considera-se como\nindicador fiscal o <i>superavit</i> primário estrutural\nque deriva das trajetórias de <i>superavit</i>\nprimário, tanto para 2014 quanto para 2015, conforme parâmetros estabelecidos\nno Projeto de Lei de Diretrizes Orçamentárias (PLDO)/2014. Dessa forma, em\ndeterminado período, o impulso fiscal equivale à variação do <i>superavit</i>\nestrutural em relação ao observado no período anterior. </div>\n\n<div>&nbsp;</div>\n\n<div class='lista1'><span class='lista1'>17.</span> Desde a última\nreunião do Copom, a mediana das projeções coletadas pelo Departamento de\nRelacionamento com Investidores e Estudos Especiais (Gerin)\npara a variação do IPCA em 2014 elevou-se de 5,92% para 6,00%. Para 2015, a\nmediana das projeções de inflação encontra-se em 5,50%.&nbsp;</div>\n\n<div>&nbsp;</div>\n\n<div class='lista1'><span class='lista1'>18.</span> O cenário de\nreferência leva em conta as hipóteses de manutenção da taxa de câmbio em\nR$2,40/US$ e da taxa Selic em 10,00% ao ano (a.a.) em todo o horizonte relevante.\nNesse cenário, a projeção para a inflação de 2014 aumentou em relação ao valor\nconsiderado na última reunião, e permanece acima da meta de 4,5% fixada pelo\nConselho Monetário Nacional (CMN). No cenário de mercado, que leva em conta as\ntrajetórias de câmbio e de juros coletadas pelo Gerin\ncom analistas de mercado, no período imediatamente anterior à reunião do Copom,\na projeção de inflação para 2014 também aumentou em relação ao valor\nconsiderado na reunião de novembro e permanece acima da meta para a inflação. Para 2015, em ambos os cenários, a projeção\nde inflação se posiciona acima da\nmeta.</div>\n\n<div>&nbsp;</div>\n\n<div><a\nname=\"_Toc361845890\"></a><a name=\"_Toc378175531\"></a></span><b>Implementação\nda política monetária</b></div>\n\n<div>&nbsp;</div>\n\n<div class='lista1'><span class='lista1'>19.</span> O Copom avalia que a\npolítica monetária deve contribuir para a consolidação de um ambiente\nmacroeconômico favorável em horizontes mais longos. Nesse sentido, reitera que,\nno regime de metas para a inflação, orienta suas decisões de acordo com os\nvalores projetados para a inflação pelo Banco Central e com base na análise de\ncenários alternativos para a evolução das principais variáveis que determinam a\ndinâmica dos preços. O Comitê entende, também, que riscos baixos para a\ninflação subjacente no curto prazo tendem a reduzir incertezas em relação ao\ncomportamento futuro da inflação plena, facilitam a avaliação de cenários por\nparte da autoridade monetária, assim como auxiliam no processo de coordenação\nde expectativas dos agentes econômicos, em particular, dos formadores de\npreços. Note-se, adicionalmente, que riscos baixos para a inflação subjacente\nno curto prazo tendem a potencializar os efeitos das ações de política\nmonetária, fazendo com que elas possam afetar de forma mais duradoura a\ndinâmica da inflação plena no futuro. Embora reconheça que outras ações de\npolítica macroeconômica podem influenciar a trajetória dos preços, o Copom\nreafirma sua visão de que cabe especificamente à política monetária manter-se\nespecialmente vigilante, para garantir que pressões detectadas em horizontes\nmais curtos não se propaguem para horizontes mais longos.</div>\n\n<div>&nbsp;</div>\n\n<div class='lista1'><span class='lista1'>20.</span> O Copom considera\nque, desde sua última reunião, os riscos para a estabilidade financeira global\npermaneceram elevados, em particular, os derivados de mudanças na inclinação da\ncurva de juros em importantes economias maduras. Apesar de identificar baixa\nprobabilidade de ocorrência de eventos extremos nos mercados financeiros\ninternacionais, o Comitê pondera que o ambiente externo permanece complexo. Para\no Comitê, amparadas em dados positivos recentemente divulgados, mantiveram-se as\nperspectivas de atividade global mais intensa ao longo do horizonte relevante\npara a política monetária. De fato, há avanços nas economias maduras, inclusive\nem países da Área do Euro, não obstante, de modo geral, permanecer limitado o\nespaço para utilização de política monetária e prevalecer cenário de restrição\nfiscal neste e nos próximos anos. Já em importantes economias emergentes, o\nritmo de atividade não tem correspondido às expectativas, em que pese a\nresiliência da demanda doméstica. O Comitê destaca ainda evidências de\nacomodação dos preços de <i>commodities</i>\nnos mercados internacionais, bem como de focos de tensão e de volatilidade nos\nmercados de moeda.</div>\n\n<div>&nbsp;</div>\n\n<div class='lista1'><span class='lista1'>21.</span> O Copom pondera que o\ncenário central contempla ritmo de expansão da atividade doméstica relativamente\nestável este ano, em comparação a 2013, e que informações recentes indicam, no\nhorizonte relevante para a política monetária, mudanças na composição da\ndemanda e da oferta agregada. A absorção interna vem se expandindo a taxas\nmaiores do que as de crescimento do PIB e, na visão do Comitê, tende a ser\nbeneficiada pelos efeitos de ações de política fiscal, da expansão moderada da\noferta de crédito (especialmente, do crédito ao consumo), do programa de\nconcessão de serviços públicos e do programa de permissão para exploração de\npetróleo, entre outros fatores. Para o Comitê, entretanto, delineia-se ambiente\nem que o consumo tenderia a continuar em crescimento, porém, em ritmo mais\nmoderado do que o observado em anos recentes; e os investimentos ganhariam\nimpulso. No que se refere ao componente externo da demanda agregada, o cenário\nde maior crescimento global, combinado com a depreciação do real, milita no\nsentido de torná-lo mais favorável ao crescimento da economia brasileira. Pelo\nlado da oferta, o Comitê avalia que emergem perspectivas mais favoráveis à\ncompetitividade da indústria e da agropecuária e que, no horizonte relevante\npara a política monetária, o setor de serviços tenderia a crescer a taxas\nmenores do que as registradas em anos recentes. É plausível afirmar que esses\ndesenvolvimentos – somados a avanços em termos de qualificação da mão de obra –\ntraduzir-se-ão numa alocação mais eficiente dos fatores de produção da economia\ne em ganhos de produtividade. O Comitê ressalta, ainda, que a velocidade de\nmaterialização das mudanças acima citadas e dos ganhos delas decorrentes\ndepende do fortalecimento da confiança de firmas e famílias.</div>\n\n<div>&nbsp;</div>\n\n<div class='lista1'><span class='lista1'>22.</span> O Copom observa que o\ncenário central para a inflação leva em conta a materialização das trajetórias\ncom as quais trabalha para as variáveis fiscais e que se criam condições para\nque, no horizonte relevante para a política monetária, o balanço do setor\npúblico se desloque para a zona de neutralidade. O Comitê nota ainda que a\ngeração de <i>superavit</i>\nprimários compatíveis com as hipóteses de trabalho contempladas nas projeções\nde inflação, de um lado, contribuiria para arrefecer o descompasso entre as\ntaxas de crescimento da demanda e da oferta; de outro, contribuiria para criar\numa percepção positiva sobre o ambiente macroeconômico no médio e no longo\nprazo. Importa destacar, também, que a geração de <i>superavit</i> primários em patamares\npróximos à média dos gerados em anos mais recentes contribuiria para diminuir o\ncusto de financiamento da dívida pública, com repercussões favoráveis sobre o\ncusto de capital de modo geral, o que estimularia o investimento privado no\nmédio e no longo prazo.</div>\n\n<div>&nbsp;</div>\n\n<div class='lista1'><span class='lista1'>23.</span> O Copom destaca que o\ncenário central também contempla expansão moderada do crédito. Ainda sobre esse\nmercado, o Comitê considera oportunas iniciativas no sentido de moderar\nconcessões de subsídios por intermédio de operações de crédito. </div>\n\n<div>&nbsp;</div>\n\n<div class='lista1'><span class='lista1'>24.</span> No mercado de\nfatores, o Copom destaca a estreita margem de ociosidade no mercado de trabalho\ne pondera que, em tais circunstâncias, um risco significativo reside na possibilidade\nde concessão de aumentos de salários incompatíveis com o crescimento da\nprodutividade e suas repercussões negativas sobre a inflação. Não obstante a\nconcessão este ano de reajuste para o salário mínimo não tão expressivo quanto\nem anos anteriores, bem como a ocorrência nos últimos trimestres de variações reais\nde salários mais condizentes com as estimativas de ganhos de produtividade do\ntrabalho, o Comitê avalia que a dinâmica salarial permanece originando pressões\ninflacionárias de custos. </div>\n\n<div>&nbsp;</div>\n\n<div class='lista1'><span class='lista1'>25.</span> O Copom avalia que a\ndepreciação e a volatilidade da taxa de câmbio verificadas nos últimos semestres\nensejam uma natural e esperada correção de preços relativos. Para o Comitê, os movimentos\nnos mercados domésticos de divisas, em certa medida, refletem perspectivas de\ntransição dos mercados financeiros internacionais na direção da normalidade,\nentre outras dimensões, em termos de liquidez e de taxas de juros. Importa\ndestacar ainda que, para o Comitê, a citada depreciação cambial constitui fonte\nde pressão inflacionária em prazos mais curtos. No entanto, os efeitos\nsecundários dela decorrentes, e que tenderiam a se materializar em prazos mais\nlongos, podem e devem ser limitados pela adequada condução da política\nmonetária. </div>\n\n<div>&nbsp;</div>\n\n<div class='lista1'><span class='lista1'>26.</span> O Copom pondera que a\nelevada variação dos índices de preços ao consumidor nos últimos doze meses\ncontribui para que a inflação ainda mostre resistência, que, a propósito, tem\nse mostrado ligeiramente acima daquela que se antecipava. Nesse contexto, inserem-se\ntambém os mecanismos formais e informais de indexação e a percepção dos agentes\neconômicos sobre a dinâmica da inflação. Tendo em vista os danos que a\npersistência desse processo causaria à tomada de decisões sobre consumo e\ninvestimentos, na visão do Comitê, faz-se necessário que, com a devida\ntempestividade, o mesmo seja revertido. Dessa forma, o Copom entende ser\napropriada a continuidade do ritmo de ajuste das condições monetárias ora em\ncurso.</div>\n\n<div>&nbsp;</div>\n\n<div class='lista1'><span class='lista1'>27.</span> Diante disso, dando\nprosseguimento ao processo de ajuste da taxa básica de juros, iniciado na\nreunião de abril de 2013, o Copom decidiu por unanimidade, neste momento,\nelevar a taxa Selic em 0,50 p.p., para 10,50% a.a.,\nsem viés.</div>\n\n<div>&nbsp;</div>\n\n<div class='lista1'><span class='lista1'>28.</span> Votaram por essa\ndecisão os seguintes membros do Comitê: Alexandre Antonio Tombini (Presidente),\nAldo Luiz Mendes, Altamir Lopes, Anthero de Moraes Meirelles, Carlos Hamilton\nVasconcelos Araújo, Luiz Awazu Pereira da Silva, Luiz\nEdson Feltrim e Sidnei Corrêa Marques.</div>\n\n<div>&nbsp;</div>\n\n<div class='lista1'><span class='lista1'>29.</span> O Copom avalia que a\ndemanda agregada tende a se apresentar relativamente robusta. De um lado, o consumo\ndas famílias tende a continuar em expansão, devido aos efeitos de fatores de\nestímulo como o crescimento da renda e a expansão moderada do crédito; de\noutro, condições financeiras favoráveis, concessão de serviços públicos,\nampliação das áreas de exploração de petróleo, entre outros, criam boas\nperspectivas para os investimentos. Esses elementos e os desenvolvimentos no\nâmbito parafiscal e no mercado de ativos são partes\nimportantes do contexto no qual decisões futuras de política monetária serão\ntomadas, com vistas a assegurar a convergência tempestiva da inflação para a\ntrajetória de metas.</div>\n\n<div>&nbsp;</div>\n\n<div class='lista1'><span class='lista1'>30.</span> O Copom ressalta que\na evidência internacional, no que é ratificada pela experiência brasileira,\nindica que taxas de inflação elevadas geram distorções que levam a aumentos dos\nriscos e deprimem os investimentos. Essas distorções se manifestam, por\nexemplo, no encurtamento dos horizontes de planejamento das famílias, empresas\ne governos, bem como na deterioração da confiança de empresários. O Comitê\nenfatiza, também, que taxas de inflação elevadas subtraem o poder de compra de\nsalários e de transferências, com repercussões negativas sobre a confiança e o\nconsumo das famílias. Por conseguinte, taxas de inflação elevadas reduzem o\npotencial de crescimento da economia, bem como de geração de empregos e de\nrenda. </div>\n\n<div>&nbsp;</div>\n\n<div class='lista1'><span class='lista1'>31.</span> O Copom destaca que,\nem momentos como o atual, a política monetária deve se manter especialmente\nvigilante, de modo a minimizar riscos de que níveis elevados de inflação, como\no observado nos últimos doze meses, persistam no horizonte relevante para a\npolítica monetária. Ao mesmo tempo, o Comitê pondera que a transmissão dos\nefeitos das ações de política monetária para a inflação ocorre com defasagens.</div>\n\n<div>&nbsp;</div>\n\n<div class='lista1'><span class='lista1'>32.</span> Ao final da reunião,\nfoi registrado que o Comitê voltará a se reunir em 25 de fevereiro de 2014,\npara as apresentações técnicas, e no dia seguinte, para deliberar sobre a\npolítica monetária, conforme estabelecido pelo Comunicado nº 24.064, de 12 de\njunho de 2013.</div>\n\n<div>&nbsp;</div>\n\n<div><b>SUMÁRIO\nDOS DADOS ANALISADOS PELO COPOM</b></div>\n\n<div>&nbsp;</div>\n\n<div><a\nname=\"_Toc361845891\"></a><a name=\"_Toc378175532\"></a></span><b>Inflação</b></div>\n\n<div>&nbsp;</div>\n\n<div class='lista1'><span class='lista1'>33.</span> O IPCA variou 0,92%\nem dezembro, ante 0,54% em novembro, alta de 5,91% em 2013, ante 5,77% nos doze\nmeses até novembro e 5,84% em 2012, de acordo com o IBGE. A aceleração mensal\nrefletiu os avanços de 0,36 p.p., para 0,92%, na variação dos preços livres e\nde 0,43 p.p., para 0,91%, na dos preços monitorados. A evolução dos preços\nlivres refletiu as acelerações dos preços dos bens não comercializáveis, de\n0,61% para 1,13%, com destaque para serviços, com variação de 1,16%, ante 0,65%\nno mês anterior, e dos produtos comercializáveis, de 0,50% para 0,68%. A\naceleração mensal do IPCA foi favorecida, principalmente, pelos avanços de\n0,36% para 1,85% nos preços do grupo transportes, com contribuição de 0,35 p.p.\npara o índice, ante 0,07 p.p. em outubro, e de 0,56% para 0,89% no grupo\nalimentação e bebidas, com contribuição de 0,22 p.p., ante 0,14 p.p. no mês\nanterior. O índice de difusão atingiu 69,32% em dezembro, ante 68,22% em\nnovembro.</div>\n\n<div>&nbsp;</div>\n\n<div class='lista1'><span class='lista1'>34.</span>\nConsiderados\nperíodos de doze meses, os preços livres desaceleraram de 7,31%, em novembro,\npara 7,29% em dezembro, reflexo da evolução de 6,20% para 6,01% na variação dos\npreços dos bens comercializáveis, enquanto os preços dos bens não\ncomercializáveis aceleraram de 8,29% para 8,43%. A elevação dos preços monitorados\natingiu 1,54%, ante 0,95% no período de doze meses encerrado em novembro. Os\npreços dos serviços aumentaram 8,75%, ante variações de 8,55% e 8,74%, nos\nperíodos de doze meses finalizados em novembro e outubro, respectivamente.</div>\n\n<div>&nbsp;</div>\n\n<div class='lista1'><span class='lista1'>35.</span>\nO\nIGP-10 variou 0,58% em janeiro, após alta de 0,44% em dezembro, de acordo com a\nFGV, refletindo acelerações nos seus três componentes. O indicador acumula\naumento de 5,55% em doze meses, comparativamente a 5,39% até dezembro.</div>\n\n<div>&nbsp;</div>\n\n<div class='lista1'><span class='lista1'>36.</span>\nO\nIPA-10 avançou 0,55% em janeiro, ante 0,38% em dezembro, acumulando alta de\n5,19% em doze meses. Os preços dos produtos industriais aumentaram 0,81% no\nmês, ante 0,35% em dezembro, acumulando alta de 8,00% em doze meses. Os preços\ndos produtos agropecuários recuaram 0,14% em janeiro, ante alta de 0,45% no mês\nanterior, acumulando queda de 1,68% em doze meses. O desempenho mensal dos\npreços dos produtos industriais evidenciou o aumento dos derivados de petróleo\ne álcool, 3,58%, com contribuição de 0,29 p.p. para o\níndice. Em relação aos produtos agropecuários, ressaltem-se as variações dos\nitens café, 13,37%, e bovinos, 2,62%, exercendo contribuições de 0,11 p.p. e 0,10 p.p.,\nrespectivamente. </div>\n\n<div>&nbsp;</div>\n\n<div class='lista1'><span class='lista1'>37.</span>\nO\nIPC-10 variou 0,76% em janeiro, ante 0,68% em dezembro, acumulando alta de\n5,48% em doze meses. A aceleração do IPC-10 em janeiro refletiu especialmente\nas elevações nos grupos transportes, 1,17% ante 0,41% em dezembro, e educação,\nleitura e recreação, 1,72% ante 0,48%, com contribuições respectivas de 0,20 p.p. e 0,13 p.p. O INCC-10 variou\n0,36% em janeiro, ante 0,26% em dezembro, com aceleração nos preços de\nmateriais, equipamentos e serviços, de 0,20% para 0,26%, e alta de 0,45% nos\ncustos de mão de obra, ante 0,32% no mês anterior. O INCC-10 acumulou variação\nde 8,18% em doze meses. </div>\n\n<div>&nbsp;</div>\n\n<div class='lista1'><span class='lista1'>38.</span> O IPP/IT variou 0,62%\nem novembro, ante -0,45% em outubro, acumulando variação de 5,04% no ano, ante\n6,84% no mesmo período de 2012. O resultado mensal do IPP/IT refletiu,\nespecialmente, as elevações de 1,22%, 1,20% e 0,72% nos preços dos segmentos\nalimentos, metalurgia e veículos automotores, reboques e carrocerias, com\ncontribuições respectivas para o índice de 0,25 p.p.,\n0,09 p.p. e 0,08 p.p. Em\ndoze meses, o IPP/IT aumentou 5,47% em novembro, ante 5,09% no mês anterior,\ndestacando-se as contribuições dos itens alimentos, 1,42 p.p.;\nmetalurgia, 0,61 p.p.; e coque, derivados do petróleo\ne biocombustíveis, 0,47 p.p.</div>\n\n<div>&nbsp;</div>\n\n<div class='lista1'><span class='lista1'>39.</span> O Índice <i>Commodities</i> – Brasil (IC-Br) avançou 2,49% em dezembro, após alta de 2,73% em\nnovembro, com avanços respectivos de 1,53%, 3,31% e 6,10% nos segmentos de <i>commodities</i> agropecuárias, metálicas e\nenergéticas. Em 2013, o IC-Br avançou 3,12%,\nresultado de valorizações de 0,23%, 4,88% e 14,70%, na ordem, nas <i>commodities </i>agropecuárias, metálicas e\nenergéticas.</div>\n\n<div>&nbsp;</div>\n\n<div><a\nname=\"_Toc378175533\"></a></span><b>Atividade\neconômica</b></div>\n\n<div>&nbsp;</div>\n\n<div class='lista1'><span class='lista1'>40.</span> O PIB recuou 0,5% no\nterceiro trimestre de 2013, em relação ao trimestre anterior, quando havia\ncrescido 1,8% (revisado), de acordo com dados dessazonalizados do IBGE. Em\nrelação ao terceiro trimestre de 2012, o PIB cresceu 2,2%. Pela ótica da\noferta, considerados dados dessazonalizados, o resultado refletiu variações de\n-3,5% na agropecuária, 0,1% na indústria e 0,1% nos serviços. O componente\ndoméstico da demanda registrou elevações no consumo das famílias, 1,0%, e do\ngoverno, 1,2% contrastando com a queda de 2,2% na FBCF, enquanto no âmbito do\nsetor externo as exportações e as importações retraíram 1,4% e 0,1%,\nrespectivamente. No acumulado do ano, o PIB elevou-se 2,4%, com crescimentos de\n8,1% na agropecuária, 2,1% nos serviços e 1,2% na indústria. A análise da\ndemanda revela, no mesmo período, contribuições de 3,6 p.p. do componente\ndoméstico, com ênfase nas variações respectivas de 6,5%, 2,4% e de 1,8% na FBCF\ne nos consumos das famílias e do governo, respectivamente; e de -1,2 p.p. do\nsetor externo, reflexo de elevações de 1,4% nas exportações e de 9,6% nas\nimportações.</div>\n\n<div>&nbsp;</div>\n\n<div class='lista1'><span class='lista1'>41.</span>\nO\nIBC-Br cresceu 0,77% em outubro em relação a setembro, quando registrara\nestabilidade, considerados dados dessazonalizados. O indicador variou 0,43% no\ntrimestre encerrado em outubro, ante o finalizado em julho, quando havia\naumentado 0,16% no mesmo tipo de comparação. Na série com dados observados, o\nIBC-Br cresceu 2,74%, em relação a outubro de 2012, ante 3,33% em setembro, na\nmesma base de comparação, e acumulou elevações de 2,81% no ano e de 2,44% no\nperíodo de doze meses terminado em outubro.</div>\n\n<div>&nbsp;</div>\n\n<div class='lista1'><span class='lista1'>42.</span>\nAs\nvendas do comércio ampliado, que inclui veículos e materiais de construção,\ncresceram 1,8% em outubro em relação ao mês anterior, de acordo com dados\ndessazonalizados da PMC do IBGE, após queda de 0,7% em setembro e alta de 0,3%\nem agosto. As vendas aumentaram 1,2% no trimestre finalizado em outubro, em\nrelação ao encerrado em julho, quando haviam crescido 0,5%, no mesmo tipo de\ncomparação. Ocorreram elevações mensais nas vendas de sete dos dez segmentos\npesquisados, com destaque para veículos e motos, partes e peças, 6,2%;\nequipamentos e materiais para escritório, informática e comunicação, 3%; e\nlivros jornais, revistas e papelaria, 1,5%. Em oposição, ressaltem-se as\nretrações de 0,4% nas vendas de hipermercados, supermercados e produtos\nalimentícios e nas de tecidos, vestuários e calçados. As vendas do comércio\nvarejista cresceram 0,2% em outubro, comparativamente ao mês anterior, após\naltas de 0,5% em setembro e de 0,9% em agosto, acumulando expansão de 2,8% no\ntrimestre encerrado em outubro, em relação ao finalizado em julho. </div>\n\n<div>&nbsp;</div>\n\n<div class='lista1'><span class='lista1'>43.</span>\nConsiderados\nos dados observados, as vendas do comércio ampliado apresentaram expansão\ninteranual de 2,2% em outubro, com ênfase no crescimento de outros artigos de\nuso pessoal e doméstico, 11,9%; artigos farmacêuticos, médicos, ortopédicos, de\nperfumaria e cosméticos, 11,4%; e equipamentos e materiais para escritório,\ninformática e comunicação, 10,5%. Em oposição, ressalte-se o recuo de 4,2% nas\nvendas de veículos e motos, partes e peças, no mesmo tipo de comparação. O\ncomércio ampliado cresceu 3,9% no período de doze meses encerrado em outubro,\ndestacando-se o aumento das vendas de outros artigos de uso pessoal e\ndoméstico, 10,9%; artigos farmacêuticos, médicos, ortopédicos, de perfumaria e\ncosméticos, 9,2%; e material de construção, 7%. Na comparação interanual e no\nperíodo de doze meses encerrado em outubro, o comércio varejista cresceu 5,3% e\n4,5%, respectivamente.</div>\n\n<div>&nbsp;</div>\n\n<div class='lista1'><span class='lista1'>44.</span>\nAs\nvendas de autoveículos pelas concessionárias, incluindo automóveis, comerciais\nleves, caminhões, e ônibus, atingiram 353,9 mil unidades em dezembro, elevação\nde 5,2% em relação a novembro, de acordo com dados da Federação Nacional da\nDistribuição de Veículos Automotores (Fenabrave), dessazonalizados pelo Banco\nCentral. Essas vendas recuaram 0,9% no quarto trimestre, em relação ao\nterceiro, quando decresceram 4,3% no mesmo tipo de comparação. Em 2013, as\nvendas de autoveículos diminuíram 1,6% relativamente ao ano anterior,\nrefletindo, principamente, a retração de 4% na venda\nde automóveis. Em oposição, as vendas de ônibus, caminhões e comerciais leves\naumentaram 20,6%, 13% e 3,6%, respectivamente.</div>\n\n<div>&nbsp;</div>\n\n<div class='lista1'><span class='lista1'>45.</span>\nO\níndice de <i>quantum</i> das importações de\nbens de capital, divulgado pela Fundação Centro de Estudos do Comércio Exterior\n(Funcex) e ajustado sazonalmente pelo Banco Central, recuou 0,8% em novembro,\nna comparação com o mês anterior. A análise dos dados observados indicou\nvariações de -5,1% em relação a novembro de 2012, de 2,7% no ano e de 2,8% no\nintervalo de doze meses terminado em novembro.</div>\n\n<div>&nbsp;</div>\n\n<div class='lista1'><span class='lista1'>46.</span>\nA\nprodução de bens de capital recuou 2,6% em novembro, acumulando expansão de\n2,9% no trimestre encerrado em novembro, relativamente ao finalizado em agosto,\nde acordo com dados dessazonalizados da Pesquisa Industrial Mensal – Produção\nFísica (PIM-PF), do IBGE. O resultado mensal refletiu, sobretudo, as retrações\nna produção das indústrias de bens de capital para fins industriais, 6,5%; e de\nequipamentos de uso misto, 2,9%. Em oposição, ressalte-se o crescimento de\n11,9% da indústria de peças agrícolas. Considerando dados observados, a\nexpansão de 9,6%, em relação a novembro de 2012, repercutiu, especialmente, a\nelevação da produção de bens de capital para construção, 55,7%; de equipamentos\nagrícolas, 18,3%; e de equipamentos de transporte, 9%.</div>\n\n<div>&nbsp;</div>\n\n<div class='lista1'><span class='lista1'>47.</span>\nA\nprodução de insumos típicos da construção civil retraiu 1,9% em novembro,\nacumulando elevação de 0,2% no trimestre encerrado em novembro, em relação ao\nfinalizado em agosto, considerando dados dessazonalizados. No período de doze\nmeses encerrado em novembro, a produção do segmento cresceu 1,7%. </div>\n\n<div>&nbsp;</div>\n\n<div class='lista1'><span class='lista1'>48.</span>\nOs\ndesembolsos do Banco Nacional de Desenvolvimento Econômico e Social (BNDES)\nsomaram R$194,4 bilhões no intervalo de doze meses encerrado em outubro,\nelevação de 35,1% em relação a igual período de 2012. Aumentaram os recursos\ndestinados a todos os segmentos: agropecuária, 71%; comércio e serviços, 66%;\ninfraestrutura, 30%; e indústria, 11%. No período, o setor de infraestrutura\nabsorveu 33% do total dos recursos liberados, seguido pelo comércio e serviços,\n30%; indústria, 28%; e agropecuária, 9%. </div>\n\n<div>&nbsp;</div>\n\n<div class='lista1'><span class='lista1'>49.</span>\nA\nprodução física da indústria geral decresceu 0,2% em novembro, em relação ao\nmês anterior, de acordo com dados dessazonalizados do IBGE, após alta de 0,6%\nem outubro. As indústrias extrativa e a de transformação variaram -3,1% e 0,1%,\nrespectivamente, no mês. Entre as categorias de uso, destaque para a produção\nde bens de capital, que recuou 2,6% em novembro, contrastando com as elevações\nem bens intermediários, 1,2%; e em bens de consumo, 0,5%. Treze das 26\natividades da indústria de transformação consideradas na pesquisa aumentaram a\nprodução, com destaque para a farmacêutica, 9,6%; de fumo, 5,4%; e de refino de\npetróleo e álcool, 4%. Em oposição, a produção diminuiu nos segmentos de\nequipamentos de instrumentação médico-hospitalar, ópticos e outros, -16%;\nedição, impressão e reprodução, -5,3%; perfumaria, sabões, detergentes e outros\nprodutos de limpeza, -4,6%; vestuário, -3,5%; têxtil, -3,5%; produtos de metal,\n-3,4%; e veículos automotores, -3,2%. A produção da indústria aumentou 0,3% no\ntrimestre encerrado em novembro, ante o finalizado em agosto, quando declinara\n0,2%, resultado das expansões de 1,9% na indústria extrativa e de 0,2% na de\ntransformação. Destacaram-se os aumentos das indústrias de diversos, 12,6%; de\nfumo, 9,5%; de perfumaria, sabões, detergentes e outros produtos de limpeza,\n7,5%; e de madeira, 5%; e as retrações das indústrias de equipamentos de\ninstrumentação médico-hospitalar, ópticos e outros, -8%; de edição, impressão e\nreprodução, -5,2%; de bebidas, -5,2%, e de vestuário, -5,1%. Considerados dados\nobservados, a produção física da indústria geral aumentou 0,4%, em relação a\nnovembro de 2012, refletindo elevações de 0,1% na indústria extrativa e de 0,4%\nna de transformação, com destaque para a expansão de 9,6% da produção de bens\nde capital, seguida pelo crescimento de 1,3% na indústria de bens\nintermediários, em contraposição à redução de 4,1% na produção de bens de\nconsumo duráveis e de 1,6% na de bens de consumo semi e não duráveis. As\nelevações respectivas de 1,1% e 1% registradas no trimestre encerrado em\nnovembro e no período de doze meses finalizado em novembro, relativamente a\nigual período do ano anterior, foram influenciadas, sobretudo, pelo crescimento\nde 17% e 11,5%, respectivamente, da indústria de bens de capital. </div>\n\n<div>&nbsp;</div>\n\n<div class='lista1'><span class='lista1'>50.</span>\nO\nNuci da indústria de transformação atingiu 84,2% em\ndezembro, queda de 0,1 p.p. em relação ao observado\nem novembro, segundo dados dessazonalizados pela FGV. Ocorreram retrações de\n1,5 p.p. na indústria de bens de capital, de 0,8 p.p. na de bens de consumo não duráveis e de 0,4 p.p. na de material de construção; elevação de 0,1 p.p. na indústria de bens de consumo duráveis; e\nestabilidade na relativa a bens intermediários. Considerada a série observada,\no Nuci elevou-se 0,1 p.p.\nem relação a dezembro de 2012, atingindo 84,9%, resultado de elevações de 1,7 p.p. em material de construção e de 0,2 p.p.\nem bens intermediários, e de reduções respectivas de 3,1 p.p.,\n1,6 p.p. e 0,2 p.p. nos\nsegmentos de bens de consumo duráveis, bens de consumo não duráveis e bens de\ncapital.</div>\n\n<div>&nbsp;</div>\n\n<div class='lista1'><span class='lista1'>51.</span>\nA\nprodução de autoveículos atingiu 235,9 mil unidades em dezembro, redução de\n5,7% em relação a novembro, de acordo com dados da Associação Nacional dos\nFabricantes de Veículos Automotores (Anfavea), dessazonalizados pelo Banco\nCentral. No quarto trimestre, a produção de autoveículos recuou 9,5% em relação\nao terceiro, quando declinara 8,7%, no mesmo tipo de comparação. Considerando\ndados observados, a produção variou -12,1% em relação a dezembro de 2012 e 9,9%\nno acumulado do ano.</div>\n\n<div>&nbsp;</div>\n\n<div class='lista1'><span class='lista1'>52.</span>\nAinda\nsegundo a Anfavea, o licenciamento de autoveículos nacionais variou 7,5% em\nrelação a novembro e -0,1% no trimestre encerrado em dezembro, de acordo com\ndados dessazonalizados pelo Banco Central. Considerados dados observados, houve\nexpansão de 0,1% em relação a dezembro de 2012 e de 1,5% em 2013. As\nexportações de autoveículos montados somaram 40,3 mil unidades em dezembro,\nvariando -2,2% em relação a igual mês do ano anterior e 26,5% no ano. Considerada\na série dessazonalizada pelo Banco Central, as exportações recuaram 8,9% em\nrelação a novembro, acumulando contração de 25% no quarto trimestre, ante o\nterceiro.</div>\n\n<div>&nbsp;</div>\n\n<div class='lista1'><span class='lista1'>53.</span> De acordo com o LSPA,\ndo IBGE, referente a dezembro, a safra de grãos do país deverá totalizar 188,2\nmilhões de toneladas em 2013, variando 16,2% em relação a 2012 e 0,7% em\nrelação ao levantamento de novembro. A projeção para o ano reflete,\nprincipalmente, o aumento de 24,3% estimado para a produção de soja,\nseguindo-se os prognósticos de crescimento de 30,4%, 13,0%, 4,1% e 3,2% para as\nculturas do trigo, milho, feijão e arroz, respectivamente. Projeta-se,\nadicionalmente, elevação de 10,0% na safra de cana-de-açúcar e retrações\nrespectivas de 14,8% e 4,7% nas de laranja e de café, na mesma base de comparação.\nAinda segundo o instituto, que elaborou o terceiro prognóstico para a safra de\n2014, estima-se que a produção de grãos atingirá 189,6 milhões de toneladas,\n0,7% superior à projetada para 2013, influenciada principalmente pela expansão\nesperada de 10,5% na produção de soja, parcialmente compensada pela retração\nestimada de 9,2% para a cultura do milho.</div>\n\n<div>&nbsp;</div>\n\n<div class='lista1'><span class='lista1'>54.</span> De acordo com a\nPesquisa Mensal de Serviços (PMS), do IBGE, a receita nominal do setor cresceu\n8,8% em outubro, ante igual mês de 2012, após variações de 9,7% em setembro e\nde 6,6% em agosto. O desempenho interanual em outubro repercutiu expansão de\ntodos os segmentos analisados: serviços prestados às famílias, 12,6%;\ntransportes e serviços auxiliares aos transportes e correio, 9,9%; serviços de\ninformação e comunicação, 7,9%; e serviços profissionais, administrativos e\ncomplementares, 7,2%. No acumulado do ano até outubro, a receita nominal do\nsetor de serviços aumentou 8,5%, com destaque para o segmento de transportes e\nserviços auxiliares aos transportes e correio, 10,8%.</div>\n\n<div>&nbsp;</div>\n\n<div><a\nname=\"_Toc378175534\"></a></span><b>Expectativas\ne sondagens</b></div>\n\n<div>&nbsp;</div>\n\n<div class='lista1'><span class='lista1'>55.</span>\nO\nÍndice de Confiança do Consumidor (ICC), considerados os dados dessazonalizados\nda Sondagem de Expectativas do Consumidor, da FGV, de abrangência nacional,\natingiu 111,5 pontos em dezembro. A retração de 1,2% em relação a novembro\nrefletiu recuos de 1,3% no Índice da Situação Atual (ISA) e de 0,4% no Índice\nde Expectativas (IE). O ICC variou -6,3% em relação a dezembro de 2012,\nresultado das quedas de 10,6% no ISA e de 3,5% no IE. </div>\n\n<div>&nbsp;</div>\n\n<div class='lista1'><span class='lista1'>56.</span>\nO\nICS, da FGV, considerados dados dessazonalizados, atingiu 118,9 pontos em\ndezembro. A expansão de 2,6% em relação a novembro refletiu acréscimos de 4,1%\nno IE e de 0,6% no ISA. O ICS recuou 3,6% em relação a dezembro de 2012,\nresultado das reduções de 3,4% no IE e de 3,8% no ISA. </div>\n\n<div>&nbsp;</div>\n\n<div class='lista1'><span class='lista1'>57.</span>\nO ICOM, calculado pela Sondagem\nConjuntural do Comércio, da FGV, atingiu 126,9 pontos em dezembro. A expansão\nmensal de 1,2%, em relação ao mesmo mês de 2012, decorreu das variações de\n2,9%, no Índice de Situação Atual (ISA-COM) e de -0,3% no Índice de\nExpectativas (IE-COM). O ICOM registrou contração de 3% no quarto trimestre, em\nrelação ao mesmo período de 2012, resultado das quedas de 6,4% no ISA-COM e de\n0,4% no IE-COM. </div>\n\n<div>&nbsp;</div>\n\n<div class='lista1'><span class='lista1'>58.</span>\nO\nÍndice de Confiança da Indústria (ICI), considerados dados dessazonalizados da\nSondagem Conjuntural da Indústria de Transformação, da FGV, atingiu 100,1\npontos em dezembro. A elevação mensal de 1,1% foi resultado dos aumentos de\n2,2% no IE e de 0,1% no ISA. O indicador recuou 5,8% em relação a dezembro de\n2012, refletindo retrações de 5,5% no IE e de 5,9% no ISA.</div>\n\n<div>&nbsp;</div>\n\n<div class='lista1'><span class='lista1'>59.</span> O Índice de Confiança\nda Construção (ICST), calculado pela Sondagem Conjuntural da Construção, da\nFGV, atingiu 115,6 pontos em dezembro, retração de 5% em relação a igual mês de\n2012. O resultado refletiu reduções de 5% no Índice de Situação Atual\n(ISA-ICST) e de 4,9% no Índice de Expectativas (IE-ICST). O ICST também\nregistrou retração no quarto trimestre de 2013, 3,9%, comparativamente a igual\nperíodo de 2012, em decorrência das contrações de 6,2% no ISA-ICST e de 1,6% no\nIE-ICST.</div>\n\n<div>&nbsp;</div>\n\n<div><a\nname=\"_Toc378175535\"></a></span><b>Mercado\nde trabalho</b></div>\n\n<div>&nbsp;</div>\n\n<div class='lista1'><span class='lista1'>60.</span> Segundo dados\ndivulgados do Cadastro Geral de Empregados e Desempregados (Caged) do MTE,\nforam gerados 47,5 mil empregos formais em novembro, ante 46,1 mil em igual mês\nde 2012, dos quais 103,3 mil no comércio e 44,8 mil em serviços, parcialmente\ncompensados pelas contrações de 34,3 mil na indústria de transformação, de 33,2\nmil na agropecuária e de 31,8 mil na construção. No acumulado do ano foram abertos\n1,2 milhão de postos e no período de doze meses encerrado em novembro, 683,2\nmil, ante 1,4 milhão e 957 mil, respectivamente, nos períodos equivalentes em\n2012. O nível de emprego formal registrou aumento mensal de 0,1% em relação a\noutubro, considerados dados dessazonalizados pelo Banco Central.</div>\n\n<div>&nbsp;</div>\n\n<div class='lista1'><span class='lista1'>61.</span> A taxa de desemprego\natingiu 4,6% em novembro, redução de 0,6 p.p. em relação a outubro e de 0,3\np.p. comparativamente a novembro de 2012, de acordo com a PME do IBGE,\nrealizada nas seis principais regiões metropolitanas do país. O resultado\nmensal refletiu aumento de 0,1% da população ocupada e queda de 0,5% da PEA. Em\nrelação a novembro de 2012, a ocupação decresceu 0,7%, ante 0,4% em outubro, na\nmesma base de comparação. A taxa de desemprego, ajustada sazonalmente, diminuiu\nde 5,3% em outubro para 5,1% em novembro. Segundo a mesma pesquisa, o\nrendimento médio real habitualmente recebido pelos trabalhadores cresceu 2% no\nmês e 3% na comparação interanual, enquanto a massa salarial real – definida\ncomo o produto do número de pessoas ocupadas pelo rendimento médio real\nhabitual do trabalho principal – variou 2% e 2,2%, respectivamente, nas mesmas\nbases de comparação.</div>\n\n<div>&nbsp;</div>\n\n<div><a\nname=\"_Toc378175536\"></a></span><b>Crédito\ne inadimplência </b></div>\n\n<div>&nbsp;</div>\n\n<div class='lista1'><span class='lista1'>62.</span> O saldo total de\ncrédito do sistema financeiro, incluindo-se as operações com recursos livres e\ndirecionados, atingiu R$2.647 bilhões em novembro, com expansões de 1,5% no mês\ne de 14,5% em doze meses. A relação crédito/PIB aumentou 0,5 p.p. em relação a\noutubro, ao alcançar 55,6%, e cresceu 2,7 p.p. comparativamente a novembro de\n2012. O saldo de operações com recursos livres, equivalente a 55,9% do estoque\ntotal do sistema financeiro, cresceu 1% no mês e 7,8% em doze meses, refletindo\nvariações de 0,3% e 7,7%, respectivamente, no saldo das operações com pessoas\nfísicas e de 1,7% e de 8% no relativo a pessoas jurídicas. Os financiamentos\ncom recursos direcionados apresentaram acréscimos respectivos de 2,1% e 24,4%,\nnas mesmas bases comparativas, com destaque para os aumentos de 2,6% e 28,3%, respectivamente,\ndo crédito rural, e de 2,3% e 34,2% dos financiamentos imobiliários, destinados\na pessoas físicas, e de 2,5% e 31,1%, na ordem, do crédito rural, entre as\noperações destinadas a pessoas jurídicas.</div>\n\n<div>&nbsp;</div>\n\n<div class='lista1'><span class='lista1'>63.</span>\nA\ntaxa média de juros das operações de crédito do sistema financeiro atingiu 20%\na.a. em novembro, elevação de 0,2 p.p. em relação a\noutubro e de 1,1 p.p. ante novembro de 2012. A taxa\nmédia atingiu 26,1% nas operações com pessoas físicas, com variações de -0,1 p.p. no mês e de 1 p.p. em doze\nmeses, e 15,1% no segmento de pessoas jurídicas, com expansões respectivas de\n0,3 p.p. e de 0,9 p.p.,\npara o mesmo tipo de comparação. </div>\n\n<div>&nbsp;</div>\n\n<div class='lista1'><span class='lista1'>64.</span> O prazo médio geral\ndas concessões de operações de crédito atingiu 94,8 meses em novembro, recuando\n0,8 mês em relação a outubro e aumentando 8,1 meses na comparação com novembro\nde 2012. No segmento de pessoas físicas, o prazo médio situou-se em 137,8\nmeses, elevando-se 1,6 mês e 17 meses, respectivamente. No segmento de pessoas\njurídicas, o prazo médio alcançou 61 meses, com retração de 2,7 meses em\nrelação a outubro e acréscimo de 0,3 mês relativamente novembro de 2012.</div>\n\n<div>&nbsp;</div>\n\n<div class='lista1'><span class='lista1'>65.</span> A taxa de\ninadimplência do sistema financeiro, correspondente às operações com atrasos\nsuperiores a noventa dias, atingiu 3,1% em novembro, recuando 0,1 p.p. em relação a outubro e 0,7 p.p.\nante novembro de 2012. Os indicadores referentes às operações com pessoas\nfísicas e jurídicas situaram-se em 4,5% e 1,9%, respectivamente, em novembro,\nambos com redução de 0,1 p.p. em relação a outubro e\nde 1,2 p.p. e 0,4 p.p., na\nordem, em doze meses.</div>\n\n<div><b>&nbsp;</b></div>\n\n<div><a\nname=\"_Toc378175537\"></a></span><b>Ambiente\nexterno</b></div>\n\n<div>&nbsp;</div>\n\n<div class='lista1'><span class='lista1'>66.</span> Nos EUA, a variação\ntrimestral anualizada do PIB do terceiro trimestre foi revisada para cima,\n4,1%, ante de 2,8% e 3,6%, respectivamente, nas duas estimativas anteriores. A\ntaxa de desemprego recuou em dezembro para 6,7%, enquanto a geração de postos\nde trabalho não rurais desacelerou para 74 mil em dezembro, de 241 mil em\nnovembro. Os preços dos imóveis residenciais seguem em elevação, o que, junto\ncom a alta das ações, tem proporcionado elevação da riqueza das famílias. Em\ndezembro, a confiança do consumidor, medida pelo índice Thomson\nReuters/Universidade de Michigan, atingiu o maior valor em cinco meses. Na Área\ndo Euro, a taxa de desemprego mantém-se há oito meses em 12,1%. O índice de\nsentimento econômico expandiu-se pelo oitavo mês consecutivo, e o PMI composto\nsubiu para 52,1 em dezembro, com média de 51,9 no último trimestre de 2013,\nante 51,4 no trimestre anterior. No Japão, as exportações seguem em expansão,\nbeneficiadas pelo crescimento da atividade econômica global e pela\ndesvalorização do iene, o que tem favorecido a expansão dos lucros corporativos\ne dos investimentos empresariais. A produção industrial média do bimestre\noutubro/novembro registrou alta de 1,7% frente à média do terceiro trimestre.\nEm dezembro, o PMI manufatura subiu para 55,2, o maior valor desde julho de\n2006, quando havia assinalado 55,4. Na China, a atividade econômica permanece\nsólida, com as exportações crescendo de forma consistente, impulsionadas pela\nalta das vendas para a Área do Euro. A despeito do recuo, na margem, do PMI\ncomposto (51,2 em dezembro), no trimestre encerrado em dezembro, o índice\nregistrou média de 51,8, ante 50,8 no trimestre anterior.</div>\n\n<div>&nbsp;</div>\n\n<div class='lista1'><span class='lista1'>67.</span>\nDesde\no último Copom, os mercados acionários se valorizaram na maior parte das\neconomias avançadas, enquanto que, nas economias emergentes, o comportamento\nfoi mais volátil, com altas nos índices da África do Sul, Índia e Indonésia, e\nrecuos nos índices do Brasil, China, Tailândia e Turquia. Os rendimentos anuais\ndos títulos de dez anos do Tesouro dos EUA subiram no período entre reuniões,\ntendo registrado trajetória de alta até o final de 2013, e de baixa desde\nentão. O dólar avançou em relação às moedas da África do Sul,\nCanadá,&nbsp;Japão, Tailândia e Turquia; mas recuou frente ao euro e ao dólar\nneozelandês. </div>\n\n<div>&nbsp;</div>\n\n<div class='lista1'><span class='lista1'>68.</span>\nNo\nmercado internacional de <i>commodities</i>,\nas agropecuárias apresentaram trajetórias distintas, com destaques para as\naltas nos preços do café, algodão, milho e da carne bovina, e recuos nos preços\ndo trigo e do açúcar. Os preços das <i>commodities</i>\nmetálicas, com exceção de minério de ferro e estanho, avançaram. Dentre as\nenergéticas, ressalte-se o recuo no preço do barril do tipo <i>Brent</i>, refletindo a retomada da produção\nna Líbia. </div>\n\n<div>&nbsp;</div>\n\n<div class='lista1'><span class='lista1'>69.</span> De acordo com o <i>International Financial Statistics</i>, do\nFundo Monetário Internacional (FMI), a variação anual do IPC global declinou\npara 3,1% em outubro, de 3,2% em setembro e 3,6% em julho, refletindo a\ndesaceleração nos aumentos de preços nas economias avançadas, de 1,6% para 1,2%\ne 1,0%, respectivamente, enquanto nas em desenvolvimento as taxas foram, na\nordem, de 6,6%, 6,2% e 6,4%. Desde a última reunião do Copom, os bancos\ncentrais dos EUA, Área do Euro, Japão e Reino Unido conservaram as respectivas\ntaxas de juros oficiais nas mínimas históricas. Nos EUA, em reunião de 18 de\ndezembro, o Fed decidiu reduzir a magnitude de seu programa de compras mensais\nde ativos em US$10 bilhões, para US$75 bilhões. As autoridades monetárias da\nTailândia, Hungria, Suécia e Romênia ampliaram a postura expansionista de suas\npolíticas, reduzindo suas respectivas taxas básicas.</div>\n\n<div>&nbsp;</div>\n\n<div><a\nname=\"_Toc378175538\"></a></span><b>Comércio\nexterior e reservas internacionais</b></div>\n\n<div>&nbsp;</div>\n\n<div class='lista1'><span class='lista1'>70.</span> A balança comercial\nbrasileira apresentou <i>superavit</i>\nde US$2,7 bilhões em dezembro, resultado de exportações de US$20,8 bilhões e\nimportações de US$18,2 bilhões. O <i>superavit</i> somou US$2,6 bilhões em 2013, ante <i>superavit</i> de\nUS$19,4 bilhões em 2012, refletindo retração de 1% das exportações e aumento de\n6,5% das importações, consideradas as médias diárias. A corrente de comércio\ntotalizou US$481,8 bilhões em 2013, expansão de 2,6% na comparação com o ano\nanterior, pelo critério de média diária.&nbsp;</div>\n\n<div>&nbsp;</div>\n\n<div class='lista1'><span class='lista1'>71.</span> As reservas\ninternacionais no conceito de liquidez, que inclui linhas com recompra,\ntotalizaram US$375,8 bilhões em dezembro, reduções de US$302 milhões no mês e\nUS$2,8 bilhões na comparação com o final de 2012. No conceito caixa, o estoque\natingiu US$358,8 bilhões, redução de US$3,6 bilhões em relação a novembro e de\nUS$14,3 bilhões comparativamente a dezembro de 2012. No mês, as liquidações de\noperações de linhas com compromisso de recompra somaram vendas de US$3,3\nbilhões, enquanto o estoque das operações registrou US$17 bilhões.</div>\n\n<div>&nbsp;</div>\n\n<div><a\nname=\"_Toc378175539\"></a></span><b>Mercado\nmonetário e operações de mercado aberto</b></div>\n\n<div>&nbsp;</div>\n\n<div class='lista1'><span class='lista1'>72.</span> Após a reunião do\nCopom de novembro, a curva de juros doméstica apresentou significativa\noscilação, terminando o período em alta no trecho curto e com relativa\nestabilidade no médio e longo prazo. Os principais fatores que contribuíram\npara a elevação das taxas foram a divulgação de índices de inflação acima do\nesperado, o movimento de valorização do dólar, as preocupações com a condução\nda política fiscal e, no âmbito externo, a decisão do <i>Federal Reserve </i>de iniciar em janeiro a redução dos estímulos\nmonetários. Entre 25 de novembro de 2013 e 13 de janeiro de 2014, as taxas de\njuros de um, três e seis meses aumentaram 0,42 p.p., 0,35 p.p. e 0,14 p.p.,\nrespectivamente. As taxas para os prazos de um e dois anos recuaram 0,09 p.p. e\n0,08 p.p., respectivamente, enquanto a de três anos subiu 0,08 p.p. A taxa real\nde juros, medida pelo quociente entre a taxa nominal de um ano e a expectativa\nde inflação (suavizada) para os próximos doze meses, apresentou elevação de\n4,42%, em 25 de novembro, para 4,46%, em 13 de janeiro, devido, principalmente,\nao recuo das expectativas inflacionárias.</div>\n\n<div>&nbsp;</div>\n\n<div class='lista1'><span class='lista1'>73.</span> No período de 26 de\nnovembro de 2013 a 13 de janeiro de 2014, o Banco Central realizou leilões de <i>swap</i> cambial tradicional com vencimentos\nentre março e setembro de 2014. Essas operações totalizaram o equivalente a\nUS$22,6 bilhões, dos quais US$12,0 bilhões referentes à rolagem de contratos\ncom vencimentos em 2 de dezembro de 2013 e 2 de janeiro de 2014. Em 13 de\njaneiro, o saldo líquido da posição passiva em câmbio do Banco Central, nesse\ninstrumento, alcançou o equivalente a US$77,0 bilhões em valor nocional.&nbsp;</div>\n\n<div>&nbsp;</div>\n\n<div class='lista1'><span class='lista1'>74.</span> Na administração da\nliquidez do mercado de reservas bancárias, o Banco Central realizou, de 26 de\nnovembro de 2013 a 13 de janeiro de 2014, diariamente, operações compromissadas\nde prazo de três meses, tomando recursos no valor total de R$48,3 bilhões e,\nsemanalmente, operações compromissadas de prazo de seis meses, tomando recursos\nno valor total de R$19,7 bilhões. O saldo diário médio do estoque das operações\nde longo prazo recuou de R$267,4 bilhões, entre 8 de outubro e 25 de novembro,\npara R$194,3 bilhões, entre 26 de novembro e 13 de janeiro. No mesmo período,\nrealizou operação compromissada com prazo de 33 dias úteis, no montante de\nR$296,6 bilhões. O Banco Central atuou, ainda, por meio de operações\ncompromissadas tomadoras de recursos de curtíssimo prazo, em 33 ocasiões. O\nsaldo diário médio tomador dessas operações de curtíssimo prazo foi de R$116,4\nbilhões no período. O saldo diário médio do estoque total dos compromissos de\nrecompra do Banco Central recuou de R$666,7 bilhões, entre 8 de outubro e 25 de\nnovembro, para R$610,0 bilhões, entre 26 de novembro e 13 de janeiro.\nConsiderando-se o período de 25 de novembro a 13 de janeiro, o estoque dos\ncompromissos de recompra aumentou de R$631,9 bilhões para R$705,7 bilhões. O\nprincipal fator que contribuiu para a expansão da liquidez foi o resgate\nlíquido de títulos pelo Tesouro Nacional.</div>\n\n</div>\n\n\n</html>\n"}